pokerchances/__init__.py
pokerchances/combtypes.py
pokerchances/poker_chances.py
pokerchances/poker_chances2.py
pokerchancestest-0.0.13.dist-info/METADATA
pokerchancestest-0.0.13.dist-info/WHEEL
pokerchancestest-0.0.13.dist-info/top_level.txt
pokerchancestest-0.0.13.dist-info/RECORD
