Metadata-Version: 2.1
Name: pokerchancestest
Version: 0.0.13
Summary: library for calculating different probabilities in poker
Home-page: UNKNOWN
Author: Tomi Bilcu
Author-email: <bilcutomi@gmail.com>
License: UNKNOWN
Keywords: python
Platform: UNKNOWN
Classifier: Development Status :: 1 - Planning
Classifier: Intended Audience :: Developers
Classifier: Programming Language :: Python :: 3
Classifier: Operating System :: Unix
Classifier: Operating System :: MacOS :: MacOS X
Classifier: Operating System :: Microsoft :: Windows
